{"document": {"publication_date": "1998", "lines_and_colors": [["Awake ye muses nine, sing me a strain divine,", {"1": "46", "0": "34", "3": "-1", "2": "77", "5": "-1", "4": "62", "7": "15", "6": "-1", "8": "64"}], ["unwind the solemn twine, and tie my Valentine!", {"1": "-1", "0": "24", "3": "34", "2": "46", "5": "41", "4": "-1", "7": "36", "6": "-1"}], ["", {"0": "-1"}], ["Oh the Earth was made for lovers, for damsel, and hopeless swain,", {"11": "46", "10": "17", "1": "-1", "0": "-1", "3": "-1", "2": "-1", "5": "-1", "4": "19", "7": "-1", "6": "64", "9": "-1", "8": "97"}], ["for sighing, and gentle whispering, and unity made of twain,", {"1": "33", "0": "-1", "3": "51", "2": "-1", "5": "-1", "4": "17", "7": "34", "6": "62", "9": "53", "8": "-1"}], ["all things do go a courting, in earth, or sea, or air,", {"11": "80", "10": "-1", "1": "24", "0": "-1", "3": "-1", "2": "-1", "5": "15", "4": "-1", "7": "-1", "6": "-1", "9": "19", "8": "-1"}], ["God hath made nothing single but thee in his world so fair!", {"11": "75", "10": "-1", "1": "15", "0": "-1", "3": "-1", "2": "34", "5": "-1", "4": "75", "7": "-1", "6": "24", "9": "-1", "8": "-1"}], ["The bride, and then the bridegroom, the two, and then the one,", {"11": "-1", "10": "-1", "1": "89", "0": "-1", "3": "-1", "2": "-1", "5": "64", "4": "-1", "7": "-1", "6": "-1", "9": "-1", "8": "-1"}], ["Adam, and Eve, his consort, the moon, and then the sun;", {"10": "-1", "1": "-1", "0": "46", "3": "-1", "2": "-1", "5": "-1", "4": "80", "7": "-1", "6": "-1", "9": "-1", "8": "-1"}], ["the life doth prove the precept, who obey shall happy be,", {"10": "-1", "1": "-1", "0": "-1", "3": "18", "2": "34", "5": "80", "4": "-1", "7": "97", "6": "-1", "9": "57", "8": "-1"}], ["who will not serve the sovreign, be hanged on fatal tree.", {"10": "46", "1": "-1", "0": "-1", "3": "21", "2": "-1", "5": "-1", "4": "-1", "7": "64", "6": "-1", "9": "24", "8": "-1"}], ["The high do seek the lowly, the great do seek the small,", {"11": "34", "10": "-1", "1": "34", "0": "-1", "3": "98", "2": "-1", "5": "69", "4": "-1", "7": "34", "6": "-1", "9": "17", "8": "-1"}], ["none cannot find who seeketh on this terrestrial ball;", {"1": "-1", "0": "-1", "3": "-1", "2": "80", "5": "-1", "4": "62", "7": "69", "6": "-1", "8": "80"}], ["The bee doth court the flower, the flower his suit receives,", {"10": "34", "1": "-1", "0": "-1", "3": "46", "2": "9", "5": "-1", "4": "-1", "7": "-1", "6": "-1", "9": "21", "8": "-1"}], ["and they make a merry wedding, whose guests are hundred leaves;", {"10": "80", "1": "-1", "0": "-1", "3": "-1", "2": "24", "5": "34", "4": "80", "7": "46", "6": "-1", "9": "3", "8": "-1"}], ["the wind doth woo the branches, the branches they are won,", {"10": "34", "1": "-1", "0": "-1", "3": "35", "2": "80", "5": "35", "4": "-1", "7": "80", "6": "-1", "9": "-1", "8": "-1"}], ["and the father fond demandeth the maiden for his son.", {"1": "-1", "0": "-1", "3": "35", "2": "-1", "5": "-1", "4": "46", "7": "-1", "6": "15", "9": "-1", "8": "-1"}], ["The storm doth walk the seashore humming a mournful tune,", {"1": "80", "0": "-1", "3": "41", "2": "97", "5": "24", "4": "-1", "7": "-1", "6": "62", "9": "15", "8": "24"}], ["the wave with eye so pensive, looketh to see the moon,", {"10": "-1", "1": "62", "0": "-1", "3": "33", "2": "-1", "5": "49", "4": "-1", "7": "-1", "6": "9", "9": "-1", "8": "-1"}], ["their spirits meet together, they make them solemn vows,", {"1": "3", "0": "-1", "3": "-1", "2": "34", "5": "24", "4": "-1", "7": "24", "6": "-1", "8": "3"}], ["no more he singeth mournful, her sadness she doth lose.", {"1": "-1", "0": "-1", "3": "62", "2": "-1", "5": "-1", "4": "34", "7": "-1", "6": "80", "9": "97", "8": "19"}], ["The worm doth woo the mortal, death claims a living bride,", {"10": "3", "1": "80", "0": "-1", "3": "41", "2": "80", "5": "24", "4": "-1", "7": "75", "6": "-1", "9": "75", "8": "-1"}], ["night unto day is married, morn unto eventide;", {"1": "-1", "0": "-1", "3": "-1", "2": "-1", "5": "-1", "4": "15", "7": "24", "6": "-1"}], ["Earth is a merry damsel, and Heaven a knight so true,", {"10": "24", "1": "-1", "0": "-1", "3": "64", "2": "-1", "5": "-1", "4": "75", "7": "-1", "6": "-1", "9": "-1", "8": "17"}], ["and Earth is quite coquettish, and he seemeth in vain to sue.", {"11": "9", "10": "-1", "1": "-1", "0": "-1", "3": "-1", "2": "-1", "5": "-1", "4": "62", "7": "15", "6": "-1", "9": "34", "8": "-1"}], ["Now to the application, to the reading of the roll,", {"1": "-1", "0": "-1", "3": "97", "2": "-1", "5": "-1", "4": "-1", "7": "-1", "6": "59", "9": "98", "8": "-1"}], ["to bringing thee to justice, and marshalling thy soul;", {"1": "75", "0": "-1", "3": "-1", "2": "69", "5": "-1", "4": "34", "7": "75", "6": "75", "8": "-1"}], ["thou art a human solo, a being cold, and lone,", {"1": "41", "0": "-1", "3": "49", "2": "-1", "5": "-1", "4": "56", "7": "33", "6": "-1", "9": "75", "8": "-1"}], ["wilt have no kind companion, thou reap'st what thou hast sown.", {"10": "75", "1": "-1", "0": "36", "3": "75", "2": "-1", "5": "-1", "4": "24", "7": "-1", "6": "75", "9": "41", "8": "-1"}], ["Hast never silent hours, and minutes all too long,", {"1": "-1", "0": "15", "3": "51", "2": "53", "5": "41", "4": "-1", "7": "-1", "6": "-1", "8": "-1"}], ["and a deal of sad reflection, and wailing instead of song?", {"10": "24", "1": "-1", "0": "-1", "3": "-1", "2": "64", "5": "19", "4": "64", "7": "46", "6": "-1", "9": "-1", "8": "-1"}], ["There's Sarah, and Eliza, and Emeline so fair,", {"1": "97", "0": "3", "3": "41", "2": "-1", "5": "41", "4": "-1", "7": "24", "6": "-1"}], ["and Harriet, and Susan, and she with curling hair!", {"1": "17", "0": "-1", "3": "33", "2": "-1", "5": "-1", "4": "-1", "7": "75", "6": "-1", "8": "-1"}], ["Thine eyes are sadly blinded, but yet thou mayest see", {"1": "38", "0": "19", "3": "91", "2": "-1", "5": "-1", "4": "97", "7": "-1", "6": "-1", "9": "-1", "8": "17"}], ["six true, and comely maidens sitting opon the tree;", {"1": "35", "0": "-1", "3": "62", "2": "-1", "5": "19", "4": "34", "7": "-1", "6": "24", "8": "62"}], ["approach that tree with caution, then up it boldly climb,", {"1": "-1", "0": "64", "3": "-1", "2": "69", "5": "-1", "4": "62", "7": "-1", "6": "-1", "9": "34", "8": "64"}], ["and seize the one thou lovest, nor care for space, or time!", {"11": "-1", "10": "-1", "1": "17", "0": "-1", "3": "-1", "2": "-1", "5": "49", "4": "-1", "7": "24", "6": "-1", "9": "-1", "8": "-1"}], ["Then bear her to the greenwood, and build for her a bower,", {"11": "17", "10": "-1", "1": "64", "0": "-1", "3": "-1", "2": "-1", "5": "46", "4": "-1", "7": "1", "6": "-1", "9": "-1", "8": "-1"}], ["and give her what she asketh, jewel, or bird, or flower;", {"10": "-1", "1": "35", "0": "-1", "3": "-1", "2": "-1", "5": "35", "4": "-1", "7": "-1", "6": "98", "9": "-1", "8": "-1"}], ["and bring the fife, and trumpet, and beat opon the drum -", {"11": "-1", "10": "17", "1": "64", "0": "-1", "3": "-1", "2": "-1", "5": "53", "4": "-1", "7": "19", "6": "-1", "9": "-1", "8": "99"}], ["and bid the world Goodmorrow, and go to glory home!", {"1": "75", "0": "-1", "3": "-1", "2": "-1", "5": "-1", "4": "97", "7": "-1", "6": "-1", "8": "-1"}]], "title": "Awake ye muses nine, sing me a strain divine", "publication": "The Poems of Emily Dickinson, Variorum Edition, Franklin, 1998", "filename": "1"}}