{"document": {"publication_date": "1998", "lines_and_colors": [["The Luxury to apprehend", {"1": "99", "0": "-1", "3": "99", "2": "-1"}], ["The Luxury 'twould be", {"1": "23", "0": "-1", "3": "-1", "2": "-1"}], ["To look at thee a single time", {"1": "-1", "0": "-1", "3": "99", "2": "-1", "5": "99", "4": "-1", "6": "-1"}], ["An Epicure of me", {"1": "99", "0": "-1", "3": "-1", "2": "-1"}], ["In whatsoever presence makes", {"1": "99", "0": "-1", "3": "99", "2": "99"}], ["Till for a further food", {"1": "-1", "0": "99", "3": "-1", "2": "-1", "4": "-1"}], ["I scarcely recollect to starve", {"1": "99", "0": "-1", "3": "-1", "2": "99", "4": "99"}], ["So first am I supplied.", {"1": "-1", "0": "-1", "3": "-1", "2": "-1", "4": "99"}], ["The Luxury to meditate", {"1": "99", "0": "-1", "3": "99", "2": "-1"}], ["The Luxury it was", {"1": "23", "0": "-1", "3": "-1", "2": "-1"}], ["To banquet on thy Countenance", {"1": "-1", "0": "-1", "3": "99", "2": "-1", "4": "99"}], ["A sumptuousness supplies", {"1": "99", "0": "-1", "2": "99"}], ["To plainer Days whose Table, far", {"1": "99", "0": "-1", "3": "-1", "2": "99", "5": "-1", "4": "-1"}], ["As Certainty can see", {"1": "99", "0": "-1", "3": "-1", "2": "-1"}], ["Is laden with a single Crumb -", {"1": "99", "0": "-1", "3": "-1", "2": "-1", "5": "99", "4": "99", "6": "-1"}], ["The Consciousness of thee -", {"1": "23", "0": "-1", "3": "-1", "2": "-1"}]], "title": "The luxury to apprehend", "publication": "The Poems of Emily Dickinson, Variorum Edition, Franklin, 1998", "filename": "1104"}}