{"document": {"publication_date": "1998", "lines_and_colors": [["The Bird must sing to earn the Crumb", {"1": "56", "0": "-1", "3": "33", "2": "-1", "5": "60", "4": "-1", "7": "77", "6": "-1"}], ["What merit have the Tune", {"1": "42", "0": "-1", "3": "-1", "2": "-1", "4": "77"}], ["No Breakfast if it guaranty", {"1": "71", "0": "-1", "3": "-1", "2": "-1", "4": "23"}], ["The Rose, content may bloom", {"1": "47", "0": "-1", "3": "-1", "2": "23", "4": "77"}], ["To gain renown of Lady's Drawer", {"1": "76", "0": "-1", "3": "-1", "2": "56", "5": "-1", "4": "-1"}], ["But if the Lady come", {"1": "-1", "0": "-1", "3": "77", "2": "-1", "4": "-1"}], ["But once a Century, the Rose", {"1": "-1", "0": "-1", "3": "-1", "2": "-1", "5": "-1", "4": "-1"}], ["Superfluous become -", {"1": "-1", "0": "-1", "2": "-1"}]], "title": "The bird must sing to earn the crumb", "publication": "The Poems of Emily Dickinson, Variorum Edition, Franklin, 1998", "filename": "1237"}}