{"document": {"publication_date": "1998", "lines_and_colors": [["Great Streets of Silence led away", {"1": "69", "0": "69", "3": "69", "2": "-1", "5": "-1", "4": "69"}], ["To Neighborhoods of Pause -", {"1": "69", "0": "-1", "3": "69", "2": "-1", "4": "-1"}], ["Here was no Notice - no Dissent -", {"1": "-1", "0": "-1", "3": "69", "2": "-1", "5": "-1", "4": "-1", "7": "-1", "6": "69"}], ["No Universe - no Laws -", {"1": "-1", "0": "-1", "3": "-1", "2": "-1", "5": "-1", "4": "69"}], ["By Clocks - 'Twas Morning", {"1": "69", "0": "-1", "3": "69", "2": "-1", "4": "-1"}], ["And for Night", {"1": "-1", "0": "-1", "2": "-1"}], ["The Bells at distance called -", {"1": "69", "0": "-1", "3": "69", "2": "-1", "5": "-1", "4": "69"}], ["But Epoch had no basis - here -", {"1": "69", "0": "-1", "3": "-1", "2": "-1", "5": "-1", "4": "32", "7": "-1", "6": "-1"}], ["For Period exhaled -", {"1": "69", "0": "-1", "2": "-1"}]], "title": "Great streets of silence led away", "publication": "The Poems of Emily Dickinson, Variorum Edition, Franklin, 1998", "filename": "1538"}}