{"document": {"publication_date": "1998", "lines_and_colors": [["Where every Bird is bold to go", {"1": "-1", "0": "-1", "3": "-1", "2": "-1", "5": "-1", "4": "98", "6": "-1"}], ["And Bees abashless play", {"1": "12", "0": "-1", "3": "45", "2": "77"}], ["The Foreigner before he knocks", {"1": "27", "0": "-1", "3": "-1", "2": "-1", "4": "84"}], ["Must thrust the Tears away -", {"1": "45", "0": "-1", "3": "-1", "2": "-1", "4": "-1"}]], "title": "Where every bird is bold to go", "publication": "The Poems of Emily Dickinson, Variorum Edition, Franklin, 1998", "filename": "1557"}}