{"document": {"publication_date": "1998", "lines_and_colors": [["The robin is a Gabriel", {"1": "-1", "0": "-1", "3": "-1", "2": "-1", "4": "-1"}], ["In humble circumstances", {"1": "67", "0": "-1", "2": "67"}], ["His dress denotes him socially", {"1": "67", "0": "-1", "3": "-1", "2": "67", "4": "67"}], ["Of transport's working classes -", {"1": "67", "0": "-1", "3": "67", "2": "67", "4": "-1"}], ["He has the punctuality", {"1": "-1", "0": "-1", "3": "67", "2": "-1"}], ["Of the New England farmer", {"1": "-1", "0": "-1", "3": "67", "2": "-1", "4": "-1"}], ["The same oblique integrity", {"1": "-1", "0": "-1", "3": "67", "2": "67"}], ["A vista - vastly warmer.", {"1": "67", "0": "-1", "3": "67", "2": "-1", "4": "66"}], ["A small, but sturdy residence", {"1": "67", "0": "-1", "3": "67", "2": "-1", "4": "67"}], ["A self denying household", {"1": "-1", "0": "-1", "3": "67", "2": "67"}], ["The guests of perspicacity", {"1": "67", "0": "-1", "3": "67", "2": "-1"}], ["Are all that cross his threshold", {"1": "-1", "0": "-1", "3": "67", "2": "-1", "5": "54", "4": "-1"}], ["As covert as a fugitive", {"1": "67", "0": "-1", "3": "-1", "2": "-1", "4": "67"}], ["Cajoling consternation", {"1": "67", "0": "67"}], ["By ditties to the enemy", {"1": "67", "0": "-1", "3": "-1", "2": "-1", "4": "-1"}], ["And silvan punctuation -", {"1": "67", "0": "-1", "2": "-1"}]], "title": "The robin is a troubadour", "publication": "The Poems of Emily Dickinson, Variorum Edition, Franklin, 1998", "filename": "2088"}}