{"document": {"publication_date": "1998", "lines_and_colors": [["I groped for him before I knew", {"1": "2", "0": "-1", "3": "-1", "2": "-1", "5": "-1", "4": "-1", "6": "20"}], ["With solemn nameless need", {"1": "85", "0": "-1", "3": "-1", "2": "29"}], ["All other bounty sudden chaff", {"1": "-1", "0": "-1", "3": "85", "2": "32", "4": "29"}], ["For this Food", {"1": "-1", "0": "-1", "2": "-1"}], ["Which others taste and spurn and  sneer -", {"1": "-1", "0": "-1", "3": "-1", "2": "75", "5": "-1", "4": "60", "7": "-1", "6": "29"}], ["Though I within suppose", {"1": "-1", "0": "-1", "3": "56", "2": "-1"}], ["That consecrated it could be", {"1": "2", "0": "-1", "3": "-1", "2": "-1", "4": "-1"}], ["The only Food that grows", {"1": "-1", "0": "-1", "3": "-1", "2": "-1"}]], "title": "I groped for him before I knew", "publication": "The Poems of Emily Dickinson, Variorum Edition, Franklin, 1998", "filename": "2189"}}