{"document": {"publication_date": "1998", "lines_and_colors": [["Of Yellow was the outer Sky", {"1": "16", "0": "-1", "3": "-1", "2": "-1", "5": "16", "4": "6"}], ["In Yellower Yellow hewn", {"1": "43", "0": "-1", "3": "46", "2": "27"}], ["Till Saffron in vermillion slid", {"1": "35", "0": "5", "3": "27", "2": "-1", "4": "5"}], ["Whose seam could not be -", {"1": "-1", "0": "-1", "3": "-1", "2": "-1", "4": "-1"}]], "title": "Of yellow was the outer sky", "publication": "The Poems of Emily Dickinson, Variorum Edition, Franklin, 1998", "filename": "2402"}}