{"document": {"publication_date": "1955", "lines_and_colors": [["For this -- accepted Breath --", {"1": "-1", "0": "-1", "3": "8", "2": "-1", "5": "-1", "4": "48"}], ["Through it -- compete with Death --", {"1": "-1", "0": "-1", "3": "62", "2": "-1", "5": "51", "4": "-1", "6": "-1"}], ["The fellow Cannot touch this Crown --", {"1": "53", "0": "-1", "3": "14", "2": "-1", "5": "14", "4": "-1", "6": "-1"}], ["By it -- my title take --", {"1": "-1", "0": "-1", "3": "-1", "2": "-1", "5": "-1", "4": "44", "6": "-1"}], ["Ah, what a royal sake", {"1": "-1", "0": "14", "3": "14", "2": "-1", "4": "14"}], ["To my nescessity -- stooped down!", {"1": "-1", "0": "-1", "3": "-1", "2": "14", "5": "-1", "4": "14"}], ["No Wilderness -- can be", {"1": "14", "0": "-1", "3": "-1", "2": "-1", "4": "-1"}], ["Where this attendeth me --", {"1": "-1", "0": "-1", "3": "-1", "2": "14", "4": "-1"}], ["No Desert Noon --", {"1": "30", "0": "-1", "3": "-1", "2": "33"}], ["No fear of frost to come", {"1": "30", "0": "-1", "3": "14", "2": "-1", "5": "-1", "4": "-1"}], ["Haunt the perennial bloom --", {"1": "-1", "0": "14", "3": "72", "2": "23", "4": "-1"}], ["But Certain June!", {"1": "-1", "0": "-1", "2": "25"}], ["Get Gabriel -- to tell -- the royal syllable --", {"1": "14", "0": "-1", "3": "-1", "2": "-1", "5": "-1", "4": "-1", "7": "79", "6": "-1", "9": "-1", "8": "53"}], ["Get Saints -- with new -- unsteady tongue --", {"1": "14", "0": "-1", "3": "-1", "2": "-1", "5": "-1", "4": "-1", "7": "53", "6": "53", "8": "-1"}], ["To say what trance below", {"1": "-1", "0": "-1", "3": "61", "2": "-1", "4": "-1"}], ["Most like their glory show --", {"1": "-1", "0": "-1", "3": "13", "2": "-1", "5": "-1", "4": "14"}], ["Fittest the Crown!", {"1": "-1", "0": "14"}]], "title": "For this -- accepted Breath --", "publication": "The Poems of Emily Dickinson, Johnson, 1955", "filename": "2655"}}