{"document": {"publication_date": "1998", "lines_and_colors": [["That after Horror - that 'twas us -", {"1": "-1", "0": "-1", "3": "-1", "2": "-1", "5": "-1", "4": "-1", "7": "-1", "6": "-1"}], ["That passed the mouldering Pier -", {"1": "63", "0": "-1", "3": "98", "2": "-1", "5": "-1", "4": "32"}], ["Just as the Granite crumb let go -", {"1": "-1", "0": "-1", "3": "12", "2": "-1", "5": "-1", "4": "72", "7": "-1", "6": "-1"}], ["Our Savior, by a Hair -", {"1": "-1", "0": "-1", "3": "-1", "2": "-1", "5": "-1", "4": "-1"}], ["A second more, had dropped too deep", {"1": "-1", "0": "-1", "3": "-1", "2": "-1", "5": "-1", "4": "53", "6": "12"}], ["For Fisherman to plumb -", {"1": "-1", "0": "-1", "3": "63", "2": "-1", "4": "-1"}], ["The very profile of the Thought", {"1": "-1", "0": "-1", "3": "-1", "2": "65", "5": "84", "4": "-1"}], ["Puts Recollection numb -", {"1": "72", "0": "62", "3": "-1", "2": "46"}], ["The possibility - to pass", {"1": "63", "0": "-1", "3": "-1", "2": "-1", "4": "32"}], ["Without a moment's Bell -", {"1": "-1", "0": "-1", "3": "46", "2": "46", "4": "-1"}], ["Into Conjecture's presence", {"1": "7", "0": "-1", "2": "86"}], ["Is like a Face of Steel -", {"1": "-1", "0": "-1", "3": "18", "2": "-1", "5": "-1", "4": "-1", "6": "-1"}], ["That suddenly looks into our's", {"1": "86", "0": "-1", "3": "-1", "2": "-1", "4": "46"}], ["With a metallic grin -", {"1": "-1", "0": "-1", "3": "32", "2": "32", "4": "-1"}], ["The Cordiality of Death -", {"1": "46", "0": "-1", "3": "-1", "2": "-1", "4": "-1"}], ["Who drills his Welcome in -", {"1": "-1", "0": "-1", "3": "-1", "2": "-1", "4": "-1"}]], "title": "That after horror - that 'twas us", "publication": "The Poems of Emily Dickinson, Variorum Edition, Franklin, 1998", "filename": "358"}}