{"document": {"publication_date": "1955", "lines_and_colors": [["The Infinite a sudden Guest", {"1": "11", "0": "-1", "3": "11", "2": "-1", "4": "11"}], ["Has been assumed", {"1": "-1", "0": "-1", "2": "11"}], ["to be -- But how can that stupendous come", {"1": "-1", "0": "-1", "3": "-1", "2": "-1", "5": "-1", "4": "-1", "7": "-1", "6": "-1"}], ["Which never went away?", {"1": "-1", "0": "-1", "3": "-1", "2": "-1"}]], "title": "The Infinite a sudden Guest", "publication": "The Poems of Emily Dickinson, Johnson, 1955", "filename": "3769"}}