{"document": {"publication_date": "1998", "lines_and_colors": [["Again - his voice is at the door -", {"1": "-1", "0": "-1", "3": "93", "2": "-1", "5": "-1", "4": "-1", "7": "41", "6": "-1", "8": "-1"}], ["I feel the old Degree -", {"1": "49", "0": "-1", "3": "-1", "2": "-1", "5": "-1", "4": "47"}], ["I hear him ask the servant", {"1": "35", "0": "-1", "3": "-1", "2": "-1", "5": "58", "4": "-1"}], ["For such an one - as me -", {"1": "-1", "0": "-1", "3": "-1", "2": "-1", "5": "-1", "4": "-1", "7": "-1", "6": "-1"}], ["I take a  flower - as I go -", {"1": "-1", "0": "-1", "3": "-1", "2": "-1", "5": "-1", "4": "-1", "7": "-1", "6": "-1", "8": "-1"}], ["My face to justify -", {"1": "86", "0": "-1", "3": "34", "2": "-1", "4": "-1"}], ["He never saw me - in  this life -", {"1": "-1", "0": "-1", "3": "-1", "2": "-1", "5": "-1", "4": "-1", "7": "-1", "6": "-1", "8": "-1"}], ["I might surprise his eye!", {"1": "-1", "0": "-1", "3": "-1", "2": "33", "4": "81"}], ["I cross the Hall with mingled steps -", {"1": "47", "0": "-1", "3": "40", "2": "-1", "5": "69", "4": "-1", "7": "-1", "6": "61"}], ["I - silent - pass the door -", {"1": "-1", "0": "-1", "3": "-1", "2": "7", "5": "-1", "4": "93", "7": "-1", "6": "58"}], ["I look on all this world contains -", {"1": "-1", "0": "-1", "3": "-1", "2": "-1", "5": "-1", "4": "-1", "7": "-1", "6": "-1"}], ["Just his face - nothing more!", {"1": "-1", "0": "-1", "3": "-1", "2": "89", "5": "-1", "4": "-1"}], ["We talk in   venture  - and in toss -", {"1": "34", "0": "-1", "3": "86", "2": "-1", "5": "-1", "4": "-1", "7": "22", "6": "-1", "8": "-1"}], ["A kind of plummet strain -", {"1": "21", "0": "-1", "3": "21", "2": "-1", "5": "-1", "4": "33"}], ["Each - sounding - shily -", {"1": "-1", "0": "-1", "3": "-1", "2": "51", "5": "-1", "4": "37"}], ["Just - how - deep -", {"1": "-1", "0": "-1", "3": "-1", "2": "-1", "5": "-1", "4": "47"}], ["The other's one - had been -", {"1": "48", "0": "-1", "3": "-1", "2": "-1", "5": "-1", "4": "-1", "6": "-1"}], ["We walk - I leave my Dog - at home -", {"10": "-1", "1": "24", "0": "-1", "3": "-1", "2": "-1", "5": "-1", "4": "24", "7": "-1", "6": "-1", "9": "49", "8": "-1"}], ["A tender - thoughtful Moon", {"1": "47", "0": "-1", "3": "21", "2": "-1", "4": "-1"}], ["Goes with us - just a little way -", {"1": "-1", "0": "-1", "3": "-1", "2": "-1", "5": "-1", "4": "-1", "7": "-1", "6": "-1", "8": "-1"}], ["And - then - we are  alone -", {"1": "-1", "0": "-1", "3": "-1", "2": "-1", "5": "-1", "4": "-1", "7": "-1", "6": "-1"}], ["Alone - if Angels are \"alone\" -", {"1": "-1", "0": "-1", "3": "4", "2": "-1", "5": "-1", "4": "-1", "6": "-1"}], ["First time they try the  sky!", {"1": "-1", "0": "-1", "3": "-1", "2": "-1", "5": "83", "4": "-1"}], ["Alone - if those \"vailed faces\" - be -", {"1": "-1", "0": "-1", "3": "-1", "2": "-1", "5": "86", "4": "31", "7": "-1", "6": "-1", "8": "-1"}], ["We cannot count -", {"1": "-1", "0": "-1", "3": "-1", "2": "37"}], ["On High!", {"1": "51", "0": "-1"}], ["I'd give - to live that hour - again -", {"1": "22", "0": "86", "3": "-1", "2": "-1", "5": "-1", "4": "58", "7": "-1", "6": "21", "9": "-1", "8": "-1"}], ["The purple - in my -", {"1": "86", "0": "-1", "3": "-1", "2": "-1", "5": "-1", "4": "-1"}], ["But He must count  -", {"1": "-1", "0": "-1", "3": "86", "2": "-1", "4": "-1"}], ["My price for every", {"1": "-1", "0": "-1", "2": "-1"}]], "title": "Again his voice is at the door", "publication": "The Poems of Emily Dickinson, Variorum Edition, Franklin, 1998", "filename": "398"}}