{"document": {"publication_date": "1998", "lines_and_colors": [["The Love a Child can show - below -", {"1": "-1", "0": "-1", "3": "-1", "2": "-1", "5": "-1", "4": "-1", "7": "-1", "6": "-1", "8": "-1"}], ["Is but a Filament - I know -", {"1": "-1", "0": "-1", "3": "54", "2": "-1", "5": "-1", "4": "-1", "7": "-1", "6": "-1"}], ["Of that Diviner - Thing -", {"1": "-1", "0": "-1", "3": "-1", "2": "63", "5": "-1", "4": "45"}], ["That faints opon the face of Noon -", {"1": "45", "0": "-1", "3": "-1", "2": "77", "5": "-1", "4": "34", "7": "-1", "6": "45"}], ["And smites the Tinder in the Sun -", {"1": "45", "0": "-1", "3": "45", "2": "-1", "5": "-1", "4": "-1", "7": "-1", "6": "-1"}], ["And hinders - Gabriel's Wing!", {"1": "45", "0": "-1", "3": "-1", "2": "-1", "4": "45"}], ["'Tis This - in Music - hints - and sways -", {"10": "-1", "1": "-1", "0": "-1", "3": "-1", "2": "-1", "5": "-1", "4": "-1", "7": "-1", "6": "45", "9": "45", "8": "-1"}], ["And far abroad - on Summer Days -", {"1": "-1", "0": "-1", "3": "-1", "2": "45", "5": "-1", "4": "-1", "7": "-1", "6": "45"}], ["- uncertain - pain -", {"1": "45", "0": "-1", "3": "-1", "2": "-1", "4": "-1"}], ["'Tis This - afflicts us in the East -", {"1": "-1", "0": "-1", "3": "45", "2": "-1", "5": "-1", "4": "-1", "7": "45", "6": "-1", "8": "-1"}], ["And tints the Transit in the West -", {"1": "45", "0": "-1", "3": "45", "2": "-1", "5": "-1", "4": "-1", "7": "-1", "6": "45"}], ["With Harrowing - Iodine!", {"1": "45", "0": "-1", "3": "45", "2": "-1"}], ["'Tis this - invites - appalls - endows -", {"1": "-1", "0": "-1", "3": "45", "2": "-1", "5": "45", "4": "-1", "7": "45", "6": "-1", "8": "-1"}], ["Flits - glimmers - proves - dissolves -", {"1": "-1", "0": "45", "3": "-1", "2": "45", "5": "-1", "4": "45", "7": "-1", "6": "45"}], ["Returns - suggests - convicts - enchants -", {"1": "-1", "0": "45", "3": "-1", "2": "45", "5": "-1", "4": "45", "7": "-1", "6": "45"}], ["Then - flings in Paradise!", {"1": "-1", "0": "-1", "3": "-1", "2": "83"}]], "title": "The love a child can show below", "publication": "The Poems of Emily Dickinson, Variorum Edition, Franklin, 1998", "filename": "416"}}