{"document": {"publication_date": "1998", "lines_and_colors": [["I meant to have but modest needs -", {"1": "39", "0": "-1", "3": "-1", "2": "-1", "5": "19", "4": "-1", "7": "-1", "6": "-1"}], ["Such as Content - and Heaven -", {"1": "-1", "0": "-1", "3": "-1", "2": "28", "5": "-1", "4": "-1", "6": "-1"}], ["Within my income - these could lie", {"1": "-1", "0": "-1", "3": "-1", "2": "39", "5": "-1", "4": "-1", "6": "27"}], ["And Life and I - keep even -", {"1": "-1", "0": "-1", "3": "-1", "2": "-1", "5": "-1", "4": "-1", "7": "-1", "6": "-1"}], ["But since the last - included both -", {"1": "-1", "0": "-1", "3": "-1", "2": "-1", "5": "37", "4": "-1", "7": "-1", "6": "-1"}], ["It would suffice my Prayer", {"1": "-1", "0": "-1", "3": "-1", "2": "19", "4": "97"}], ["But just for one - to stipulate -", {"1": "-1", "0": "-1", "3": "-1", "2": "-1", "5": "-1", "4": "-1", "7": "-1", "6": "74"}], ["And Grace would grant the Pair -", {"1": "74", "0": "-1", "3": "37", "2": "-1", "5": "19", "4": "-1", "6": "-1"}], ["And so - opon this wise - I prayed -", {"1": "-1", "0": "-1", "3": "39", "2": "-1", "5": "19", "4": "-1", "7": "-1", "6": "-1", "9": "-1", "8": "37"}], ["Great Spirit - Give to me", {"1": "-1", "0": "9", "3": "17", "2": "-1", "5": "-1", "4": "-1"}], ["A Heaven not so large as Your's,", {"1": "-1", "0": "-1", "3": "-1", "2": "-1", "5": "-1", "4": "39", "6": "17"}], ["But large enough - for me -", {"1": "37", "0": "-1", "3": "-1", "2": "-1", "5": "-1", "4": "-1", "6": "-1"}], ["A Smile suffused Jehovah's face -", {"1": "-1", "0": "-1", "3": "19", "2": "39", "5": "-1", "4": "19"}], ["The Cherubim - withdrew -", {"1": "28", "0": "-1", "3": "17", "2": "-1", "4": "-1"}], ["Grave Saints stole out to look at me -", {"1": "98", "0": "-1", "3": "-1", "2": "13", "5": "-1", "4": "-1", "7": "-1", "6": "-1", "8": "-1"}], ["And showed their dimples - too -", {"1": "27", "0": "-1", "3": "94", "2": "-1", "5": "-1", "4": "-1", "6": "-1"}], ["I left the Place - with all my might -", {"1": "14", "0": "-1", "3": "37", "2": "-1", "5": "-1", "4": "-1", "7": "-1", "6": "-1", "9": "-1", "8": "-1"}], ["I threw my Prayer away -", {"1": "19", "0": "-1", "3": "90", "2": "-1", "5": "-1", "4": "-1"}], ["The Quiet Ages picked it up -", {"1": "28", "0": "-1", "3": "75", "2": "27", "5": "-1", "4": "-1", "6": "-1"}], ["And Judgment - twinkled - too -", {"1": "37", "0": "-1", "3": "37", "2": "-1", "5": "-1", "4": "-1", "6": "-1"}], ["That one so honest - be extant -", {"1": "-1", "0": "-1", "3": "19", "2": "-1", "5": "-1", "4": "-1", "7": "-1", "6": "39"}], ["It take the Tale for true -", {"1": "-1", "0": "-1", "3": "17", "2": "-1", "5": "17", "4": "-1", "6": "-1"}], ["That \"Whatsoever Ye shall ask -", {"1": "14", "0": "-1", "3": "-1", "2": "27", "5": "-1", "4": "-1"}], ["Itself be given You\" -", {"1": "-1", "0": "-1", "3": "-1", "2": "-1", "4": "-1"}], ["But I, grown shrewder - scan the Skies", {"1": "-1", "0": "-1", "3": "27", "2": "17", "5": "14", "4": "-1", "7": "19", "6": "-1"}], ["With a suspicious Air -", {"1": "-1", "0": "-1", "3": "37", "2": "19", "4": "-1"}], ["As Children - swindled for the first", {"1": "-1", "0": "-1", "3": "17", "2": "-1", "5": "-1", "4": "-1", "6": "-1"}], ["All Swindlers - be - infer -", {"1": "87", "0": "-1", "3": "-1", "2": "-1", "5": "-1", "4": "-1"}]], "title": "I meant to have but modest needs", "publication": "The Poems of Emily Dickinson, Variorum Edition, Franklin, 1998", "filename": "949"}}