{"document": {"publication_date": "1998", "lines_and_colors": [["The Heaven vests for Each", {"1": "-1", "0": "-1", "3": "-1", "2": "77", "4": "-1"}], ["In that small Deity", {"1": "-1", "0": "-1", "3": "-1", "2": "41"}], ["It craved the grace to worship", {"1": "20", "0": "-1", "3": "52", "2": "-1", "5": "41", "4": "-1"}], ["Some bashful Summer's Day -", {"1": "67", "0": "-1", "3": "-1", "2": "-1", "4": "-1"}], ["Half shrinking from the Glory", {"1": "9", "0": "25", "3": "-1", "2": "-1", "4": "-1"}], ["It importuned to see", {"1": "28", "0": "-1", "3": "-1", "2": "-1"}], ["Till these faint Tabernacles drop", {"1": "-1", "0": "23", "3": "43", "2": "-1", "4": "11"}], ["In full Eternity -", {"1": "11", "0": "-1", "3": "-1", "2": "-1"}], ["How imminent the Venture -", {"1": "92", "0": "-1", "3": "92", "2": "-1", "4": "-1"}], ["As One should sue a Star -", {"1": "-1", "0": "-1", "3": "11", "2": "-1", "5": "-1", "4": "-1", "6": "-1"}], ["For His mean sake to leave the Row", {"1": "-1", "0": "-1", "3": "25", "2": "-1", "5": "21", "4": "-1", "7": "92", "6": "-1"}], ["And entertain Despair -", {"1": "14", "0": "-1", "3": "-1", "2": "-1"}], ["A Clemency so common -", {"1": "41", "0": "-1", "3": "89", "2": "-1", "4": "-1"}], ["We almost cease to fear -", {"1": "-1", "0": "-1", "3": "-1", "2": "25", "5": "-1", "4": "92"}], ["Enabling the minutest -", {"1": "-1", "0": "12", "3": "-1", "2": "95"}], ["And furthest - to adore -", {"1": "27", "0": "-1", "3": "-1", "2": "-1", "4": "-1"}]], "title": "The heaven vests for each", "publication": "The Poems of Emily Dickinson, Variorum Edition, Franklin, 1998", "filename": "955"}}