{"document": {"publication": "The Poems of Emily Dickinson, Variorum Edition, Franklin, 1998", "full_text": "<xhtml:p class=\"text_p\"><xhtml:span class=\"text_edgespan\">&nbsp;</xhtml:span></xhtml:p><xhtml:p class=\"text_p\"><xhtml:span class=\"text_edgespan\">&nbsp;&nbsp;&nbsp;&nbsp;</xhtml:span><xhtml:span class=\"text_coloredword\" style=\"color:#d440ff\">Despair's&nbsp;</xhtml:span><xhtml:span class=\"text_coloredword\" style=\"color:#502c44\">advantage&nbsp;</xhtml:span><xhtml:span class=\"text_word\">is&nbsp;</xhtml:span><xhtml:span class=\"text_coloredword\" style=\"color:#d440ff\">achieved&nbsp;</xhtml:span></xhtml:p><xhtml:p class=\"text_p\"><xhtml:span class=\"text_edgespan\">&nbsp;&nbsp;&nbsp;&nbsp;</xhtml:span><xhtml:span class=\"text_word\">By&nbsp;</xhtml:span><xhtml:span class=\"text_coloredword\" style=\"color:#d440ff\">suffering&nbsp;</xhtml:span><xhtml:span class=\"text_word\">-&nbsp;</xhtml:span><xhtml:span class=\"text_coloredword\" style=\"color:#44c4ff\">Despair&nbsp;</xhtml:span><xhtml:span class=\"text_word\">-&nbsp;</xhtml:span></xhtml:p><xhtml:p class=\"text_p\"><xhtml:span class=\"text_edgespan\">&nbsp;&nbsp;&nbsp;&nbsp;</xhtml:span><xhtml:span class=\"text_word\">To&nbsp;</xhtml:span><xhtml:span class=\"text_word\">be&nbsp;</xhtml:span><xhtml:span class=\"text_coloredword\" style=\"color:#d440ff\">assisted&nbsp;</xhtml:span><xhtml:span class=\"text_word\">of&nbsp;</xhtml:span><xhtml:span class=\"text_coloredword\" style=\"color:#d440ff\">Reverse&nbsp;</xhtml:span></xhtml:p><xhtml:p class=\"text_p\"><xhtml:span class=\"text_edgespan\">&nbsp;&nbsp;&nbsp;&nbsp;</xhtml:span><xhtml:span class=\"text_word\">One&nbsp;</xhtml:span><xhtml:span class=\"text_word\">must&nbsp;</xhtml:span><xhtml:span class=\"text_coloredword\" style=\"color:#d440ff\">Reverse&nbsp;</xhtml:span><xhtml:span class=\"text_word\">have&nbsp;</xhtml:span><xhtml:span class=\"text_coloredword\" style=\"color:#88b0e0\">bore&nbsp;</xhtml:span><xhtml:span class=\"text_word\">-&nbsp;</xhtml:span></xhtml:p><xhtml:p class=\"text_p\"><xhtml:span class=\"text_edgespan\">&nbsp;&nbsp;&nbsp;&nbsp;</xhtml:span><xhtml:span class=\"text_word\">The&nbsp;</xhtml:span><xhtml:span class=\"text_coloredword\" style=\"color:#d440ff\">Worthiness&nbsp;</xhtml:span><xhtml:span class=\"text_word\">of&nbsp;</xhtml:span><xhtml:span class=\"text_coloredword\" style=\"color:#d440ff\">Suffering&nbsp;</xhtml:span><xhtml:span class=\"text_word\">like&nbsp;</xhtml:span></xhtml:p><xhtml:p class=\"text_p\"><xhtml:span class=\"text_edgespan\">&nbsp;&nbsp;&nbsp;&nbsp;</xhtml:span><xhtml:span class=\"text_word\">The&nbsp;</xhtml:span><xhtml:span class=\"text_coloredword\" style=\"color:#d440ff\">Worthiness&nbsp;</xhtml:span><xhtml:span class=\"text_word\">of&nbsp;</xhtml:span><xhtml:span class=\"text_coloredword\" style=\"color:#80ff60\">Death&nbsp;</xhtml:span></xhtml:p><xhtml:p class=\"text_p\"><xhtml:span class=\"text_edgespan\">&nbsp;&nbsp;&nbsp;&nbsp;</xhtml:span><xhtml:span class=\"text_word\">Is&nbsp;</xhtml:span><xhtml:span class=\"text_coloredword\" style=\"color:#d440ff\">ascertained&nbsp;</xhtml:span><xhtml:span class=\"text_word\">by&nbsp;</xhtml:span><xhtml:span class=\"text_coloredword\" style=\"color:#88b0e0\">tasting&nbsp;</xhtml:span><xhtml:span class=\"text_word\">-&nbsp;</xhtml:span></xhtml:p><xhtml:p class=\"text_p\"><xhtml:span class=\"text_edgespan\">&nbsp;&nbsp;&nbsp;&nbsp;</xhtml:span><xhtml:span class=\"text_word\">As&nbsp;</xhtml:span><xhtml:span class=\"text_word\">can&nbsp;</xhtml:span><xhtml:span class=\"text_word\">no&nbsp;</xhtml:span><xhtml:span class=\"text_word\">other&nbsp;</xhtml:span><xhtml:span class=\"text_coloredword\" style=\"color:#1c48ff\">Mouth&nbsp;</xhtml:span></xhtml:p><xhtml:p class=\"text_p\"><xhtml:span class=\"text_edgespan\">&nbsp;&nbsp;&nbsp;&nbsp;</xhtml:span><xhtml:span class=\"text_word\">Of&nbsp;</xhtml:span><xhtml:span class=\"text_coloredword\" style=\"color:#b0bcff\">Savors&nbsp;</xhtml:span><xhtml:span class=\"text_word\">-&nbsp;</xhtml:span><xhtml:span class=\"text_coloredword\" style=\"color:#1c48ff\">make&nbsp;</xhtml:span><xhtml:span class=\"text_word\">us&nbsp;</xhtml:span><xhtml:span class=\"text_coloredword\" style=\"color:#d440ff\">conscious&nbsp;</xhtml:span><xhtml:span class=\"text_word\">-&nbsp;</xhtml:span></xhtml:p><xhtml:p class=\"text_p\"><xhtml:span class=\"text_edgespan\">&nbsp;&nbsp;&nbsp;&nbsp;</xhtml:span><xhtml:span class=\"text_word\">As&nbsp;</xhtml:span><xhtml:span class=\"text_word\">did&nbsp;</xhtml:span><xhtml:span class=\"text_word\">ourselves&nbsp;</xhtml:span><xhtml:span class=\"text_coloredword\" style=\"color:#8cdcff\">partake&nbsp;</xhtml:span><xhtml:span class=\"text_word\">-&nbsp;</xhtml:span></xhtml:p><xhtml:p class=\"text_p\"><xhtml:span class=\"text_edgespan\">&nbsp;&nbsp;&nbsp;&nbsp;</xhtml:span><xhtml:span class=\"text_coloredword\" style=\"color:#ff903c\">Affliction&nbsp;</xhtml:span><xhtml:span class=\"text_coloredword\" style=\"color:#d440ff\">feels&nbsp;</xhtml:span><xhtml:span class=\"text_coloredword\" style=\"color:#d440ff\">impalpable&nbsp;</xhtml:span></xhtml:p><xhtml:p class=\"text_p\"><xhtml:span class=\"text_edgespan\">&nbsp;&nbsp;&nbsp;&nbsp;</xhtml:span><xhtml:span class=\"text_word\">Until&nbsp;</xhtml:span><xhtml:span class=\"text_word\">Ourselves&nbsp;</xhtml:span><xhtml:span class=\"text_word\">are&nbsp;</xhtml:span><xhtml:span class=\"text_coloredword\" style=\"color:#502c44\">struck&nbsp;</xhtml:span><xhtml:span class=\"text_word\">-&nbsp;</xhtml:span></xhtml:p>", "title": "Despair's advantage is achieved", "line_count": 12, "filename": "1146", "publication_date": "1998", "lines_and_colors": [[["Despair's", "advantage", "is", "achieved"], {"1": "31", "0": "97", "3": "97"}], [["By", "suffering", "-", "Despair", "-"], {"1": "97", "3": "47"}], [["To", "be", "assisted", "of", "Reverse"], {"2": "97", "4": "97"}], [["One", "must", "Reverse", "have", "bore", "-"], {"2": "97", "4": "95"}], [["The", "Worthiness", "of", "Suffering", "like"], {"1": "97", "3": "97"}], [["The", "Worthiness", "of", "Death"], {"1": "97", "3": "9"}], [["Is", "ascertained", "by", "tasting", "-"], {"1": "97", "3": "95"}], [["As", "can", "no", "other", "Mouth"], {"4": "0"}], [["Of", "Savors", "-", "make", "us", "conscious", "-"], {"1": "48", "3": "0", "5": "97"}], [["As", "did", "ourselves", "partake", "-"], {"3": "81"}], [["Affliction", "feels", "impalpable"], {"1": "97", "0": "8", "2": "97"}], [["Until", "Ourselves", "are", "struck", "-"], {"3": "31"}]]}}