{"document": {"publication": "The Poems of Emily Dickinson, Variorum Edition, Franklin, 1998", "full_text": "<xhtml:p class=\"text_p\"><xhtml:span class=\"text_edgespan\">&nbsp;</xhtml:span></xhtml:p><xhtml:p class=\"text_p\"><xhtml:span class=\"text_edgespan\">&nbsp;&nbsp;&nbsp;&nbsp;</xhtml:span><xhtml:span class=\"text_word\">That&nbsp;</xhtml:span><xhtml:span class=\"text_coloredword\" style=\"color:#6cffa8\">Bells&nbsp;</xhtml:span><xhtml:span class=\"text_word\">should&nbsp;</xhtml:span><xhtml:span class=\"text_coloredword\" style=\"color:#6cffa8\">ring,&nbsp;</xhtml:span><xhtml:span class=\"text_word\">till&nbsp;</xhtml:span><xhtml:span class=\"text_word\">all&nbsp;</xhtml:span><xhtml:span class=\"text_word\">should&nbsp;</xhtml:span><xhtml:span class=\"text_word\">know&nbsp;</xhtml:span></xhtml:p><xhtml:p class=\"text_p\"><xhtml:span class=\"text_edgespan\">&nbsp;&nbsp;&nbsp;&nbsp;</xhtml:span><xhtml:span class=\"text_word\">A&nbsp;</xhtml:span><xhtml:span class=\"text_coloredword\" style=\"color:#6cffa8\">soul&nbsp;</xhtml:span><xhtml:span class=\"text_word\">had&nbsp;</xhtml:span><xhtml:span class=\"text_word\">gone&nbsp;</xhtml:span><xhtml:span class=\"text_word\">to&nbsp;</xhtml:span><xhtml:span class=\"text_coloredword\" style=\"color:#ffb218\">Heaven&nbsp;</xhtml:span></xhtml:p><xhtml:p class=\"text_p\"><xhtml:span class=\"text_edgespan\">&nbsp;&nbsp;&nbsp;&nbsp;</xhtml:span><xhtml:span class=\"text_word\">Would&nbsp;</xhtml:span><xhtml:span class=\"text_word\">seem&nbsp;</xhtml:span><xhtml:span class=\"text_word\">to&nbsp;</xhtml:span><xhtml:span class=\"text_word\">me&nbsp;</xhtml:span><xhtml:span class=\"text_word\">the&nbsp;</xhtml:span><xhtml:span class=\"text_word\">more&nbsp;</xhtml:span><xhtml:span class=\"text_word\">the&nbsp;</xhtml:span><xhtml:span class=\"text_word\">way&nbsp;</xhtml:span></xhtml:p><xhtml:p class=\"text_p\"><xhtml:span class=\"text_edgespan\">&nbsp;&nbsp;&nbsp;&nbsp;</xhtml:span><xhtml:span class=\"text_word\">A&nbsp;</xhtml:span><xhtml:span class=\"text_coloredword\" style=\"color:#e0e464\">good&nbsp;</xhtml:span><xhtml:span class=\"text_coloredword\" style=\"color:#9c88ff\">news&nbsp;</xhtml:span><xhtml:span class=\"text_word\">should&nbsp;</xhtml:span><xhtml:span class=\"text_word\">be&nbsp;</xhtml:span><xhtml:span class=\"text_word\">given&nbsp;</xhtml:span><xhtml:span class=\"text_word\">-&nbsp;</xhtml:span></xhtml:p>", "title": "Of tolling bell I ask the cause?", "line_count": 4, "filename": "1244", "publication_date": "1998", "lines_and_colors": [[["That", "Bells", "should", "ring,", "till", "all", "should", "know"], {"1": "29", "3": "29"}], [["A", "soul", "had", "gone", "to", "Heaven"], {"1": "29", "5": "5"}], [["Would", "seem", "to", "me", "the", "more", "the", "way"], {}], [["A", "good", "news", "should", "be", "given", "-"], {"1": "40", "2": "42"}]]}}