{"document": {"publication": "The Poems of Emily Dickinson, Variorum Edition, Franklin, 1998", "full_text": "<xhtml:p class=\"text_p\"><xhtml:span class=\"text_edgespan\">&nbsp;</xhtml:span></xhtml:p><xhtml:p class=\"text_p\"><xhtml:span class=\"text_edgespan\">&nbsp;&nbsp;&nbsp;&nbsp;</xhtml:span><xhtml:span class=\"text_word\">The&nbsp;</xhtml:span><xhtml:span class=\"text_coloredword\" style=\"color:#ffa444\">good&nbsp;</xhtml:span><xhtml:span class=\"text_word\">Will&nbsp;</xhtml:span><xhtml:span class=\"text_word\">of&nbsp;</xhtml:span><xhtml:span class=\"text_word\">a&nbsp;</xhtml:span><xhtml:span class=\"text_coloredword\" style=\"color:#6cffa8\">Flower&nbsp;</xhtml:span></xhtml:p><xhtml:p class=\"text_p\"><xhtml:span class=\"text_edgespan\">&nbsp;&nbsp;&nbsp;&nbsp;</xhtml:span><xhtml:span class=\"text_word\">The&nbsp;</xhtml:span><xhtml:span class=\"text_coloredword\" style=\"color:#84c4e0\">Man&nbsp;</xhtml:span><xhtml:span class=\"text_word\">who&nbsp;</xhtml:span><xhtml:span class=\"text_word\">would&nbsp;</xhtml:span><xhtml:span class=\"text_coloredword\" style=\"color:#ffec8c\">possess&nbsp;</xhtml:span></xhtml:p><xhtml:p class=\"text_p\"><xhtml:span class=\"text_edgespan\">&nbsp;&nbsp;&nbsp;&nbsp;</xhtml:span><xhtml:span class=\"text_word\">Must&nbsp;</xhtml:span><xhtml:span class=\"text_word\">first&nbsp;</xhtml:span><xhtml:span class=\"text_coloredword\" style=\"color:#c478ff\">present&nbsp;</xhtml:span><xhtml:span class=\"text_coloredword\" style=\"color:#84c4e0\">Certificate&nbsp;</xhtml:span></xhtml:p><xhtml:p class=\"text_p\"><xhtml:span class=\"text_edgespan\">&nbsp;&nbsp;&nbsp;&nbsp;</xhtml:span><xhtml:span class=\"text_word\">Of&nbsp;</xhtml:span><xhtml:span class=\"text_coloredword\" style=\"color:#84c4e0\">minted&nbsp;</xhtml:span><xhtml:span class=\"text_coloredword\" style=\"color:#6cffa8\">Holiness.&nbsp;</xhtml:span></xhtml:p>", "title": "The good will of a flower", "line_count": 4, "filename": "1276", "publication_date": "1998", "lines_and_colors": [[["The", "good", "Will", "of", "a", "Flower"], {"1": "24", "5": "29"}], [["The", "Man", "who", "would", "possess"], {"1": "18", "4": "15"}], [["Must", "first", "present", "Certificate"], {"3": "18", "2": "94"}], [["Of", "minted", "Holiness."], {"1": "18", "2": "29"}]]}}