{"document": {"publication": "The Poems of Emily Dickinson, Variorum Edition, Franklin, 1998", "full_text": "<xhtml:p class=\"text_p\"><xhtml:span class=\"text_edgespan\">&nbsp;</xhtml:span></xhtml:p><xhtml:p class=\"text_p\"><xhtml:span class=\"text_edgespan\">&nbsp;&nbsp;&nbsp;&nbsp;</xhtml:span><xhtml:span class=\"text_word\">Where&nbsp;</xhtml:span><xhtml:span class=\"text_word\">I&nbsp;</xhtml:span><xhtml:span class=\"text_word\">am&nbsp;</xhtml:span><xhtml:span class=\"text_word\">not&nbsp;</xhtml:span><xhtml:span class=\"text_coloredword\" style=\"color:#ff5460\">afraid&nbsp;</xhtml:span><xhtml:span class=\"text_word\">to&nbsp;</xhtml:span><xhtml:span class=\"text_word\">go&nbsp;</xhtml:span></xhtml:p><xhtml:p class=\"text_p\"><xhtml:span class=\"text_edgespan\">&nbsp;&nbsp;&nbsp;&nbsp;</xhtml:span><xhtml:span class=\"text_word\">I&nbsp;</xhtml:span><xhtml:span class=\"text_word\">can&nbsp;</xhtml:span><xhtml:span class=\"text_coloredword\" style=\"color:#04c8ff\">confide&nbsp;</xhtml:span><xhtml:span class=\"text_word\">my&nbsp;</xhtml:span><xhtml:span class=\"text_coloredword\" style=\"color:#7864ff\">flower.&nbsp;</xhtml:span></xhtml:p>", "title": "Where I am not afraid to go", "line_count": 2, "filename": "1315", "publication_date": "1998", "lines_and_colors": [[["Where", "I", "am", "not", "afraid", "to", "go"], {"4": "7"}], [["I", "can", "confide", "my", "flower."], {"2": "55", "4": "93"}]]}}