{"document": {"publication": "The Poems of Emily Dickinson, Variorum Edition, Franklin, 1998", "full_text": "<xhtml:p class=\"text_p\"><xhtml:span class=\"text_edgespan\">&nbsp;</xhtml:span></xhtml:p><xhtml:p class=\"text_p\"><xhtml:span class=\"text_edgespan\">&nbsp;&nbsp;&nbsp;&nbsp;</xhtml:span><xhtml:span class=\"text_word\">'Tis&nbsp;</xhtml:span><xhtml:span class=\"text_word\">my&nbsp;</xhtml:span><xhtml:span class=\"text_word\">first&nbsp;</xhtml:span><xhtml:span class=\"text_coloredword\" style=\"color:#a060c4\">night&nbsp;</xhtml:span><xhtml:span class=\"text_coloredword\" style=\"color:#a060c4\">beneath&nbsp;</xhtml:span><xhtml:span class=\"text_word\">the&nbsp;</xhtml:span><xhtml:span class=\"text_coloredword\" style=\"color:#94b8f8\">Sun&nbsp;</xhtml:span></xhtml:p><xhtml:p class=\"text_p\"><xhtml:span class=\"text_edgespan\">&nbsp;&nbsp;&nbsp;&nbsp;</xhtml:span><xhtml:span class=\"text_word\">If&nbsp;</xhtml:span><xhtml:span class=\"text_word\">I&nbsp;</xhtml:span><xhtml:span class=\"text_word\">should&nbsp;</xhtml:span><xhtml:span class=\"text_coloredword\" style=\"color:#a060c4\">spend&nbsp;</xhtml:span><xhtml:span class=\"text_word\">it&nbsp;</xhtml:span><xhtml:span class=\"text_word\">here&nbsp;</xhtml:span><xhtml:span class=\"text_word\">-&nbsp;</xhtml:span></xhtml:p><xhtml:p class=\"text_p\"><xhtml:span class=\"text_edgespan\">&nbsp;&nbsp;&nbsp;&nbsp;</xhtml:span><xhtml:span class=\"text_word\">Above&nbsp;</xhtml:span><xhtml:span class=\"text_word\">him&nbsp;</xhtml:span><xhtml:span class=\"text_word\">is&nbsp;</xhtml:span><xhtml:span class=\"text_word\">too&nbsp;</xhtml:span><xhtml:span class=\"text_coloredword\" style=\"color:#a8e0ff\">low&nbsp;</xhtml:span><xhtml:span class=\"text_word\">a&nbsp;</xhtml:span><xhtml:span class=\"text_coloredword\" style=\"color:#9064a8\">hight&nbsp;</xhtml:span></xhtml:p><xhtml:p class=\"text_p\"><xhtml:span class=\"text_edgespan\">&nbsp;&nbsp;&nbsp;&nbsp;</xhtml:span><xhtml:span class=\"text_word\">For&nbsp;</xhtml:span><xhtml:span class=\"text_word\">his&nbsp;</xhtml:span><xhtml:span class=\"text_coloredword\" style=\"color:#94d4f0\">Barometer&nbsp;</xhtml:span></xhtml:p><xhtml:p class=\"text_p\"><xhtml:span class=\"text_edgespan\">&nbsp;&nbsp;&nbsp;&nbsp;</xhtml:span><xhtml:span class=\"text_word\">Who&nbsp;</xhtml:span><xhtml:span class=\"text_coloredword\" style=\"color:#94b8f8\">Airs&nbsp;</xhtml:span><xhtml:span class=\"text_word\">of&nbsp;</xhtml:span><xhtml:span class=\"text_coloredword\" style=\"color:#94b8f8\">expectation&nbsp;</xhtml:span><xhtml:span class=\"text_coloredword\" style=\"color:#84c4e0\">breathes&nbsp;</xhtml:span></xhtml:p><xhtml:p class=\"text_p\"><xhtml:span class=\"text_edgespan\">&nbsp;&nbsp;&nbsp;&nbsp;</xhtml:span><xhtml:span class=\"text_word\">And&nbsp;</xhtml:span><xhtml:span class=\"text_coloredword\" style=\"color:#94d4f0\">takes&nbsp;</xhtml:span><xhtml:span class=\"text_word\">the&nbsp;</xhtml:span><xhtml:span class=\"text_coloredword\" style=\"color:#649cff\">Wind&nbsp;</xhtml:span><xhtml:span class=\"text_word\">at&nbsp;</xhtml:span><xhtml:span class=\"text_coloredword\" style=\"color:#ff5460\">prime&nbsp;</xhtml:span><xhtml:span class=\"text_word\">-&nbsp;</xhtml:span></xhtml:p><xhtml:p class=\"text_p\"><xhtml:span class=\"text_edgespan\">&nbsp;&nbsp;&nbsp;&nbsp;</xhtml:span><xhtml:span class=\"text_word\">But&nbsp;</xhtml:span><xhtml:span class=\"text_coloredword\" style=\"color:#e0e464\">Distance&nbsp;</xhtml:span><xhtml:span class=\"text_word\">his&nbsp;</xhtml:span><xhtml:span class=\"text_coloredword\" style=\"color:#649cff\">Delights&nbsp;</xhtml:span><xhtml:span class=\"text_coloredword\" style=\"color:#a060c4\">confides&nbsp;</xhtml:span></xhtml:p><xhtml:p class=\"text_p\"><xhtml:span class=\"text_edgespan\">&nbsp;&nbsp;&nbsp;&nbsp;</xhtml:span><xhtml:span class=\"text_word\">To&nbsp;</xhtml:span><xhtml:span class=\"text_word\">those&nbsp;</xhtml:span><xhtml:span class=\"text_word\">who&nbsp;</xhtml:span><xhtml:span class=\"text_coloredword\" style=\"color:#b46090\">visit&nbsp;</xhtml:span><xhtml:span class=\"text_word\">him&nbsp;</xhtml:span></xhtml:p>", "title": "'Tis my first night beneath the sun", "line_count": 8, "filename": "1518", "publication_date": "1998", "lines_and_colors": [[["'Tis", "my", "first", "night", "beneath", "the", "Sun"], {"3": "53", "4": "53", "6": "77"}], [["If", "I", "should", "spend", "it", "here", "-"], {"3": "53"}], [["Above", "him", "is", "too", "low", "a", "hight"], {"4": "38", "6": "50"}], [["For", "his", "Barometer"], {"2": "92"}], [["Who", "Airs", "of", "expectation", "breathes"], {"1": "77", "3": "77", "4": "18"}], [["And", "takes", "the", "Wind", "at", "prime", "-"], {"1": "92", "3": "90", "5": "7"}], [["But", "Distance", "his", "Delights", "confides"], {"1": "40", "3": "90", "4": "53"}], [["To", "those", "who", "visit", "him"], {"3": "86"}]]}}