{"document": {"publication_date": "1998", "lines_and_colors": [["Somewhere opon the general Earth", {"1": "24", "0": "-1", "3": "59", "2": "-1", "4": "-1"}], ["Itself exist Today -", {"1": "27", "0": "-1", "3": "-1", "2": "-1"}], ["The Magic passive but extant", {"1": "90", "0": "-1", "3": "-1", "2": "33", "4": "90"}], ["That consecrated me -", {"1": "71", "0": "-1", "3": "-1", "2": "-1"}], ["Indifferent Seasons doubtless play", {"1": "83", "0": "81", "3": "90", "2": "50"}], ["Where I for right to be -", {"1": "-1", "0": "-1", "3": "-1", "2": "-1", "5": "-1", "4": "-1", "6": "-1"}], ["Would pay each Atom that I am", {"1": "93", "0": "-1", "3": "-1", "2": "-1", "5": "-1", "4": "-1", "6": "-1"}], ["But Immortality -", {"1": "81", "0": "-1", "2": "-1"}], ["Reserving that but just to prove", {"1": "-1", "0": "76", "3": "-1", "2": "-1", "5": "76", "4": "-1"}], ["Another Date of Thee -", {"1": "67", "0": "-1", "3": "16", "2": "-1", "4": "-1"}], ["Oh God of Width, do not for us", {"1": "-1", "0": "-1", "3": "24", "2": "-1", "5": "-1", "4": "-1", "7": "-1", "6": "-1"}], ["Curtail Eternity!", {"0": "-1"}]], "title": "Somewhere opon the general earth", "publication": "The Poems of Emily Dickinson, Variorum Edition, Franklin, 1998", "filename": "1624"}}