{"document": {"publication": "The Poems of Emily Dickinson, Variorum Edition, Franklin, 1998", "full_text": "<xhtml:p class=\"text_p\"><xhtml:span class=\"text_edgespan\">&nbsp;</xhtml:span></xhtml:p><xhtml:p class=\"text_p\"><xhtml:span class=\"text_edgespan\">&nbsp;&nbsp;&nbsp;&nbsp;</xhtml:span><xhtml:span class=\"text_word\">Whether&nbsp;</xhtml:span><xhtml:span class=\"text_word\">they&nbsp;</xhtml:span><xhtml:span class=\"text_word\">have&nbsp;</xhtml:span><xhtml:span class=\"text_coloredword\" style=\"color:#c8b4f0\">forgotten&nbsp;</xhtml:span></xhtml:p><xhtml:p class=\"text_p\"><xhtml:span class=\"text_edgespan\">&nbsp;&nbsp;&nbsp;&nbsp;</xhtml:span><xhtml:span class=\"text_word\">Or&nbsp;</xhtml:span><xhtml:span class=\"text_word\">are&nbsp;</xhtml:span><xhtml:span class=\"text_coloredword\" style=\"color:#ecff56\">forgetting&nbsp;</xhtml:span><xhtml:span class=\"text_word\">now&nbsp;</xhtml:span></xhtml:p><xhtml:p class=\"text_p\"><xhtml:span class=\"text_edgespan\">&nbsp;&nbsp;&nbsp;&nbsp;</xhtml:span><xhtml:span class=\"text_word\">Or&nbsp;</xhtml:span><xhtml:span class=\"text_word\">never&nbsp;</xhtml:span><xhtml:span class=\"text_coloredword\" style=\"color:#ff607c\">remembered&nbsp;</xhtml:span><xhtml:span class=\"text_word\">-&nbsp;</xhtml:span></xhtml:p><xhtml:p class=\"text_p\"><xhtml:span class=\"text_edgespan\">&nbsp;&nbsp;&nbsp;&nbsp;</xhtml:span><xhtml:span class=\"text_coloredword\" style=\"color:#ff2878\">Safer&nbsp;</xhtml:span><xhtml:span class=\"text_word\">not&nbsp;</xhtml:span><xhtml:span class=\"text_word\">to&nbsp;</xhtml:span><xhtml:span class=\"text_word\">know&nbsp;</xhtml:span><xhtml:span class=\"text_word\">-&nbsp;</xhtml:span></xhtml:p><xhtml:p class=\"text_p\"><xhtml:span class=\"text_edgespan\">&nbsp;&nbsp;&nbsp;&nbsp;</xhtml:span><xhtml:span class=\"text_coloredword\" style=\"color:#ff2878\">Miseries&nbsp;</xhtml:span><xhtml:span class=\"text_word\">of&nbsp;</xhtml:span><xhtml:span class=\"text_coloredword\" style=\"color:#ff903c\">conjecture&nbsp;</xhtml:span></xhtml:p><xhtml:p class=\"text_p\"><xhtml:span class=\"text_edgespan\">&nbsp;&nbsp;&nbsp;&nbsp;</xhtml:span><xhtml:span class=\"text_word\">Are&nbsp;</xhtml:span><xhtml:span class=\"text_word\">a&nbsp;</xhtml:span><xhtml:span class=\"text_coloredword\" style=\"color:#ff04c4\">softer&nbsp;</xhtml:span><xhtml:span class=\"text_word\">wo&nbsp;</xhtml:span></xhtml:p><xhtml:p class=\"text_p\"><xhtml:span class=\"text_edgespan\">&nbsp;&nbsp;&nbsp;&nbsp;</xhtml:span><xhtml:span class=\"text_word\">Than&nbsp;</xhtml:span><xhtml:span class=\"text_word\">a&nbsp;</xhtml:span><xhtml:span class=\"text_coloredword\" style=\"color:#ff7ae0\">Fact&nbsp;</xhtml:span><xhtml:span class=\"text_word\">of&nbsp;</xhtml:span><xhtml:span class=\"text_coloredword\" style=\"color:#ecff56\">Iron&nbsp;</xhtml:span></xhtml:p><xhtml:p class=\"text_p\"><xhtml:span class=\"text_edgespan\">&nbsp;&nbsp;&nbsp;&nbsp;</xhtml:span><xhtml:span class=\"text_coloredword\" style=\"color:#ff04c4\">Hardened&nbsp;</xhtml:span><xhtml:span class=\"text_word\">with&nbsp;</xhtml:span><xhtml:span class=\"text_word\">I&nbsp;</xhtml:span><xhtml:span class=\"text_word\">know&nbsp;</xhtml:span><xhtml:span class=\"text_word\">-&nbsp;</xhtml:span></xhtml:p>", "title": "Whether they have forgotten", "line_count": 8, "filename": "1783", "publication_date": "1998", "lines_and_colors": [[["Whether", "they", "have", "forgotten"], {"3": "67"}], [["Or", "are", "forgetting", "now"], {"2": "43"}], [["Or", "never", "remembered", "-"], {"2": "16"}], [["Safer", "not", "to", "know", "-"], {"0": "84"}], [["Miseries", "of", "conjecture"], {"0": "84", "2": "8"}], [["Are", "a", "softer", "wo"], {"2": "44"}], [["Than", "a", "Fact", "of", "Iron"], {"2": "2", "4": "43"}], [["Hardened", "with", "I", "know", "-"], {"0": "44"}]]}}