{"document": {"publication": "The Poems of Emily Dickinson, Variorum Edition, Franklin, 1998", "full_text": "<xhtml:p class=\"text_p\"><xhtml:span class=\"text_edgespan\">&nbsp;</xhtml:span></xhtml:p><xhtml:p class=\"text_p\"><xhtml:span class=\"text_edgespan\">&nbsp;&nbsp;&nbsp;&nbsp;</xhtml:span><xhtml:span class=\"text_coloredword\" style=\"color:#b46090\">Hope&nbsp;</xhtml:span><xhtml:span class=\"text_word\">is&nbsp;</xhtml:span><xhtml:span class=\"text_word\">a&nbsp;</xhtml:span><xhtml:span class=\"text_coloredword\" style=\"color:#8474ff\">strange&nbsp;</xhtml:span><xhtml:span class=\"text_coloredword\" style=\"color:#c06cff\">invention&nbsp;</xhtml:span><xhtml:span class=\"text_word\">-&nbsp;</xhtml:span></xhtml:p><xhtml:p class=\"text_p\"><xhtml:span class=\"text_edgespan\">&nbsp;&nbsp;&nbsp;&nbsp;</xhtml:span><xhtml:span class=\"text_word\">A&nbsp;</xhtml:span><xhtml:span class=\"text_coloredword\" style=\"color:#84c4e0\">Patent&nbsp;</xhtml:span><xhtml:span class=\"text_word\">of&nbsp;</xhtml:span><xhtml:span class=\"text_word\">the&nbsp;</xhtml:span><xhtml:span class=\"text_coloredword\" style=\"color:#28ff42\">Heart&nbsp;</xhtml:span><xhtml:span class=\"text_word\">-&nbsp;</xhtml:span></xhtml:p><xhtml:p class=\"text_p\"><xhtml:span class=\"text_edgespan\">&nbsp;&nbsp;&nbsp;&nbsp;</xhtml:span><xhtml:span class=\"text_word\">In&nbsp;</xhtml:span><xhtml:span class=\"text_coloredword\" style=\"color:#28ff42\">unremitting&nbsp;</xhtml:span><xhtml:span class=\"text_coloredword\" style=\"color:#84c4e0\">action&nbsp;</xhtml:span></xhtml:p><xhtml:p class=\"text_p\"><xhtml:span class=\"text_edgespan\">&nbsp;&nbsp;&nbsp;&nbsp;</xhtml:span><xhtml:span class=\"text_word\">Yet&nbsp;</xhtml:span><xhtml:span class=\"text_word\">never&nbsp;</xhtml:span><xhtml:span class=\"text_coloredword\" style=\"color:#28ff42\">wearing&nbsp;</xhtml:span><xhtml:span class=\"text_word\">out&nbsp;</xhtml:span><xhtml:span class=\"text_word\">-&nbsp;</xhtml:span></xhtml:p><xhtml:p class=\"text_p\"><xhtml:span class=\"text_edgespan\">&nbsp;&nbsp;&nbsp;&nbsp;</xhtml:span><xhtml:span class=\"text_word\">Of&nbsp;</xhtml:span><xhtml:span class=\"text_word\">this&nbsp;</xhtml:span><xhtml:span class=\"text_coloredword\" style=\"color:#84c4e0\">electric&nbsp;</xhtml:span><xhtml:span class=\"text_coloredword\" style=\"color:#84c4e0\">adjunct&nbsp;</xhtml:span></xhtml:p><xhtml:p class=\"text_p\"><xhtml:span class=\"text_edgespan\">&nbsp;&nbsp;&nbsp;&nbsp;</xhtml:span><xhtml:span class=\"text_word\">Not&nbsp;</xhtml:span><xhtml:span class=\"text_word\">anything&nbsp;</xhtml:span><xhtml:span class=\"text_word\">is&nbsp;</xhtml:span><xhtml:span class=\"text_word\">known&nbsp;</xhtml:span></xhtml:p><xhtml:p class=\"text_p\"><xhtml:span class=\"text_edgespan\">&nbsp;&nbsp;&nbsp;&nbsp;</xhtml:span><xhtml:span class=\"text_word\">But&nbsp;</xhtml:span><xhtml:span class=\"text_word\">it's&nbsp;</xhtml:span><xhtml:span class=\"text_coloredword\" style=\"color:#84c4e0\">unique&nbsp;</xhtml:span><xhtml:span class=\"text_coloredword\" style=\"color:#84c4e0\">momentum&nbsp;</xhtml:span></xhtml:p><xhtml:p class=\"text_p\"><xhtml:span class=\"text_edgespan\">&nbsp;&nbsp;&nbsp;&nbsp;</xhtml:span><xhtml:span class=\"text_coloredword\" style=\"color:#84c4e0\">Embellish&nbsp;</xhtml:span><xhtml:span class=\"text_word\">all&nbsp;</xhtml:span><xhtml:span class=\"text_word\">we&nbsp;</xhtml:span><xhtml:span class=\"text_word\">own&nbsp;</xhtml:span><xhtml:span class=\"text_word\">-&nbsp;</xhtml:span></xhtml:p>", "title": "Hope is a strange invention", "line_count": 8, "filename": "1938", "publication_date": "1998", "lines_and_colors": [[["Hope", "is", "a", "strange", "invention", "-"], {"0": "86", "3": "39", "4": "73"}], [["A", "Patent", "of", "the", "Heart", "-"], {"1": "18", "4": "11"}], [["In", "unremitting", "action"], {"1": "11", "2": "18"}], [["Yet", "never", "wearing", "out", "-"], {"2": "11"}], [["Of", "this", "electric", "adjunct"], {"3": "18", "2": "18"}], [["Not", "anything", "is", "known"], {}], [["But", "it's", "unique", "momentum"], {"3": "18", "2": "18"}], [["Embellish", "all", "we", "own", "-"], {"0": "18"}]]}}