{"document": {"publication": "The Poems of Emily Dickinson, Variorum Edition, Franklin, 1998", "full_text": "<xhtml:p class=\"text_p\"><xhtml:span class=\"text_edgespan\">&nbsp;</xhtml:span></xhtml:p><xhtml:p class=\"text_p\"><xhtml:span class=\"text_edgespan\">&nbsp;&nbsp;&nbsp;&nbsp;</xhtml:span><xhtml:span class=\"text_word\">Is&nbsp;</xhtml:span><xhtml:span class=\"text_word\">it&nbsp;</xhtml:span><xhtml:span class=\"text_coloredword\" style=\"color:#48dc40\">true,&nbsp;</xhtml:span><xhtml:span class=\"text_coloredword\" style=\"color:#bce454\">dear&nbsp;</xhtml:span><xhtml:span class=\"text_coloredword\" style=\"color:#ffe05e\">Sue?&nbsp;</xhtml:span></xhtml:p><xhtml:p class=\"text_p\"><xhtml:span class=\"text_edgespan\">&nbsp;&nbsp;&nbsp;&nbsp;</xhtml:span><xhtml:span class=\"text_word\">Are&nbsp;</xhtml:span><xhtml:span class=\"text_word\">there&nbsp;</xhtml:span><xhtml:span class=\"text_word\">two?&nbsp;</xhtml:span></xhtml:p><xhtml:p class=\"text_p\"><xhtml:span class=\"text_edgespan\">&nbsp;&nbsp;&nbsp;&nbsp;</xhtml:span><xhtml:span class=\"text_word\">I&nbsp;</xhtml:span><xhtml:span class=\"text_word\">should'nt&nbsp;</xhtml:span><xhtml:span class=\"text_word\">like&nbsp;</xhtml:span><xhtml:span class=\"text_word\">to&nbsp;</xhtml:span><xhtml:span class=\"text_word\">come&nbsp;</xhtml:span></xhtml:p><xhtml:p class=\"text_p\"><xhtml:span class=\"text_edgespan\">&nbsp;&nbsp;&nbsp;&nbsp;</xhtml:span><xhtml:span class=\"text_word\">For&nbsp;</xhtml:span><xhtml:span class=\"text_coloredword\" style=\"color:#58d4e8\">fear&nbsp;</xhtml:span><xhtml:span class=\"text_word\">of&nbsp;</xhtml:span><xhtml:span class=\"text_coloredword\" style=\"color:#a4c4ff\">joggling&nbsp;</xhtml:span><xhtml:span class=\"text_word\">Him!&nbsp;</xhtml:span></xhtml:p><xhtml:p class=\"text_p\"><xhtml:span class=\"text_edgespan\">&nbsp;&nbsp;&nbsp;&nbsp;</xhtml:span><xhtml:span class=\"text_word\">If&nbsp;</xhtml:span><xhtml:span class=\"text_word\">you&nbsp;</xhtml:span><xhtml:span class=\"text_word\">could&nbsp;</xhtml:span><xhtml:span class=\"text_coloredword\" style=\"color:#70e498\">shut&nbsp;</xhtml:span><xhtml:span class=\"text_word\">him&nbsp;</xhtml:span><xhtml:span class=\"text_word\">up&nbsp;</xhtml:span></xhtml:p><xhtml:p class=\"text_p\"><xhtml:span class=\"text_edgespan\">&nbsp;&nbsp;&nbsp;&nbsp;</xhtml:span><xhtml:span class=\"text_word\">In&nbsp;</xhtml:span><xhtml:span class=\"text_word\">a&nbsp;</xhtml:span><xhtml:span class=\"text_coloredword\" style=\"color:#a4c4ff\">Coffee&nbsp;</xhtml:span><xhtml:span class=\"text_coloredword\" style=\"color:#540c8c\">Cup,&nbsp;</xhtml:span></xhtml:p><xhtml:p class=\"text_p\"><xhtml:span class=\"text_edgespan\">&nbsp;&nbsp;&nbsp;&nbsp;</xhtml:span><xhtml:span class=\"text_word\">Or&nbsp;</xhtml:span><xhtml:span class=\"text_coloredword\" style=\"color:#70e498\">tie&nbsp;</xhtml:span><xhtml:span class=\"text_word\">him&nbsp;</xhtml:span><xhtml:span class=\"text_word\">to&nbsp;</xhtml:span><xhtml:span class=\"text_word\">a&nbsp;</xhtml:span><xhtml:span class=\"text_coloredword\" style=\"color:#70e498\">pin&nbsp;</xhtml:span></xhtml:p><xhtml:p class=\"text_p\"><xhtml:span class=\"text_edgespan\">&nbsp;&nbsp;&nbsp;&nbsp;</xhtml:span><xhtml:span class=\"text_word\">Till&nbsp;</xhtml:span><xhtml:span class=\"text_word\">I&nbsp;</xhtml:span><xhtml:span class=\"text_word\">got&nbsp;</xhtml:span><xhtml:span class=\"text_word\">in&nbsp;</xhtml:span><xhtml:span class=\"text_word\">-&nbsp;</xhtml:span></xhtml:p><xhtml:p class=\"text_p\"><xhtml:span class=\"text_edgespan\">&nbsp;&nbsp;&nbsp;&nbsp;</xhtml:span><xhtml:span class=\"text_word\">Or&nbsp;</xhtml:span><xhtml:span class=\"text_coloredword\" style=\"color:#ffe05e\">make&nbsp;</xhtml:span><xhtml:span class=\"text_word\">him&nbsp;</xhtml:span><xhtml:span class=\"text_coloredword\" style=\"color:#b4d0b4\">fast&nbsp;</xhtml:span></xhtml:p><xhtml:p class=\"text_p\"><xhtml:span class=\"text_edgespan\">&nbsp;&nbsp;&nbsp;&nbsp;</xhtml:span><xhtml:span class=\"text_word\">To&nbsp;</xhtml:span><xhtml:span class=\"text_coloredword\" style=\"color:#58d4e8\">\"Toby's\"&nbsp;</xhtml:span><xhtml:span class=\"text_coloredword\" style=\"color:#ffe05e\">fist&nbsp;</xhtml:span><xhtml:span class=\"text_word\">-&nbsp;</xhtml:span></xhtml:p><xhtml:p class=\"text_p\"><xhtml:span class=\"text_edgespan\">&nbsp;&nbsp;&nbsp;&nbsp;</xhtml:span><xhtml:span class=\"text_coloredword\" style=\"color:#540c8c\">Hist!&nbsp;</xhtml:span><xhtml:span class=\"text_coloredword\" style=\"color:#58d4e8\">Whist!&nbsp;</xhtml:span><xhtml:span class=\"text_word\">I'd&nbsp;</xhtml:span><xhtml:span class=\"text_word\">come!&nbsp;</xhtml:span></xhtml:p>", "title": "Is it true, dear Sue?", "line_count": 11, "filename": "281", "publication_date": "1998", "lines_and_colors": [[["Is", "it", "true,", "dear", "Sue?"], {"3": "79", "2": "82", "4": "21"}], [["Are", "there", "two?"], {}], [["I", "should'nt", "like", "to", "come"], {}], [["For", "fear", "of", "joggling", "Him!"], {"1": "99", "3": "63"}], [["If", "you", "could", "shut", "him", "up"], {"3": "96"}], [["In", "a", "Coffee", "Cup,"], {"3": "3", "2": "63"}], [["Or", "tie", "him", "to", "a", "pin"], {"1": "96", "5": "96"}], [["Till", "I", "got", "in", "-"], {}], [["Or", "make", "him", "fast"], {"1": "21", "3": "78"}], [["To", "\"Toby's\"", "fist", "-"], {"1": "99", "2": "21"}], [["Hist!", "Whist!", "I'd", "come!"], {"1": "99", "0": "3"}]]}}